{
  "space:base": {
    "git":"https://github.com/meteor-space/base.git",
    "version": "b2368e7fb25d01bddfb16164b20806ce07080200"
  },
  "space:messaging": {
    "git":"https://github.com/meteor-space/messaging.git",
    "version": "207fe48806c6c63e1a6d3973d38050f9686ca99c"
  },
  "space:ui": {
    "git":"https://github.com/meteor-space/ui.git",
    "version": "9281635b5f0030d8053036c463a80487543b7edd"
  },
  "space:flux": {
    "git":"https://github.com/meteor-space/flux.git",
    "version": "4c496386a5ce0715bf8a50c281ae2dda35a83d61"
  }
}
